pylabwons/__init__.py
pylabwons/constants.py
pylabwons/api/__init__.py
pylabwons/api/generic.py
pylabwons/core/__init__.py
pylabwons/core/backtest.py
pylabwons/core/detector.py
pylabwons/core/indicator.py
pylabwons/core/viewer.py
pylabwons/core/fetch/__init__.py
pylabwons/core/fetch/market.py
pylabwons/schema/__init__.py
pylabwons/schema/ohlcv.py
pylabwons/schema/trace.py
pylabwons/utils/__init__.py
pylabwons/utils/datadict.py
pylabwons/utils/tradingdates.py
pylabwons-1.0.1.dist-info/licenses/LICENSE
pylabwons-1.0.1.dist-info/METADATA
pylabwons-1.0.1.dist-info/WHEEL
pylabwons-1.0.1.dist-info/top_level.txt
pylabwons-1.0.1.dist-info/RECORD
