Metadata-Version: 2.4
Name: pylabwons
Version: 1.0.1
Summary: SNOWBALL REVERSES LABWONS
Requires-Python: >=3.8
License-File: LICENSE
Requires-Dist: pandas
Requires-Dist: plotly
Requires-Dist: pyarrow
Requires-Dist: pykrx
Requires-Dist: numpy
Requires-Dist: scipy
Requires-Dist: ta
Dynamic: license-file
